calculator/__init__.py
calculator/cli.py
calculator/core.py
ark_calculator-0.1.1.dist-info/METADATA
ark_calculator-0.1.1.dist-info/WHEEL
ark_calculator-0.1.1.dist-info/entry_points.txt
ark_calculator-0.1.1.dist-info/top_level.txt
ark_calculator-0.1.1.dist-info/RECORD
