Metadata-Version: 2.4
Name: ark-calculator
Version: 0.1.1
Summary: Just a test calculator package
Author-email: Anil <ark845612@gmail.com>
Project-URL: Homepage, https://github.com/Anonymous961/python_package_sample
Project-URL: Issues, https://github.com/Anonymous961/python_package_sample/issues
